MANIFEST.in
README.rst
setup.py
zcbot_celery_sdk/__init__.py
zcbot_celery_sdk/client.py
zcbot_celery_sdk/monitor.py
zcbot_celery_sdk.egg-info/PKG-INFO
zcbot_celery_sdk.egg-info/SOURCES.txt
zcbot_celery_sdk.egg-info/dependency_links.txt
zcbot_celery_sdk.egg-info/requires.txt
zcbot_celery_sdk.egg-info/top_level.txt
zcbot_celery_sdk/common/__init__.py
zcbot_celery_sdk/common/decator.py
zcbot_celery_sdk/common/exceptions.py
zcbot_celery_sdk/common/keys.py
zcbot_celery_sdk/common/thread_pool.py
zcbot_celery_sdk/common/utils.py
zcbot_celery_sdk/model/__init__.py
zcbot_celery_sdk/model/callback.py
zcbot_celery_sdk/model/param.py
zcbot_celery_sdk/service/__init__.py
zcbot_celery_sdk/service/base.py
zcbot_celery_sdk/service/oss.py
zcbot_celery_sdk/service/sku_search.py
zcbot_celery_sdk/service/tax.py