Metadata-Version: 2.1
Name: zcbot-celery-sdk
Version: 0.0.44
Summary: zcbot celery sdk for zsodata
Home-page: http://www.zsodata.com
Author: zsodata
Author-email: team@zso.io
License: BSD License
Platform: all
Requires-Python: >=3.7
